inaccel/keras/__init__.py
inaccel/keras/applications/__init__.py
inaccel/keras/applications/imagenet_utils.py
inaccel/keras/applications/mobilenet.py
inaccel/keras/applications/resnet50.py
inaccel/keras/preprocessing/__init__.py
inaccel/keras/preprocessing/image.py
inaccel_keras-2.7.0.2.dist-info/LICENSE
inaccel_keras-2.7.0.2.dist-info/METADATA
inaccel_keras-2.7.0.2.dist-info/NOTICE
inaccel_keras-2.7.0.2.dist-info/WHEEL
inaccel_keras-2.7.0.2.dist-info/top_level.txt
inaccel_keras-2.7.0.2.dist-info/zip-safe
inaccel_keras-2.7.0.2.dist-info/RECORD
