Metadata-Version: 2.1
Name: inaccel-keras
Version: 2.7.0.2
Summary: InAccel keras-like package
Home-page: https://docs.inaccel.com
Author: InAccel
Author-email: info@inaccel.com
License: Apache-2.0
Keywords: InAccel Coral,FPGA,inaccel,keras
Classifier: Development Status :: 5 - Production/Stable
Classifier: License :: OSI Approved :: Apache Software License
Classifier: Operating System :: POSIX :: Linux
Classifier: Programming Language :: Python
Classifier: Programming Language :: Python :: 3
Classifier: Programming Language :: Python :: 3.8
Classifier: Programming Language :: Python :: 3.9
Classifier: Programming Language :: Python :: 3.10
Requires-Python: >=3.8
License-File: LICENSE
License-File: NOTICE
Requires-Dist: coral-api (==2.*)
Requires-Dist: keras (==2.7.0)
Requires-Dist: h5py
Requires-Dist: keras-preprocessing
Requires-Dist: opencv-python
